[
  {
    "product_id": "EAR001",
    "product_name": "小米真无线蓝牙耳机 Air2 SE",
    "model": "TWSEJ04WM",
    "brand": "Xiaomi",
    "category": "earphone",
    "product_level": "入门",
    "wearing_type": "半入耳式",
    "reference_price": 199.0,
    "single_weight_g": 4.7,
    "single_battery_h": 5.0,
    "total_battery_h": 20.0,
    "anc_supported": false,
    "anc_depth_db": null,
    "dual_device": false,
    "low_latency": true,
    "bluetooth_version": 5.0,
    "waterproof": "IP54",
    "codec": null,
    "driver_size_mm": null,
    "source_url": "https://www.mi.com/jp/mi-true-wireless-earphone-2-basic/",
    "manual_available": "是",
    "data_status": "部分缺失",
    "update_date": "2026-07-16",
    "remarks": null,
    "manual_url": "https://cdn.cnbj1.fds.api.mi-img.com/ics-resources/articles/63be5a60aba6bc20c6275e46.html",
    "official_url": "https://www.mi.com/jp/mi-true-wireless-earphone-2-basic/"
  },
  {
    "product_id": "EAR002",
    "product_name": "Xiaomi 真无线降噪耳机 3",
    "model": "M2111E1",
    "brand": "Xiaomi",
    "category": "earphone",
    "product_level": "高端",
    "wearing_type": "入耳式",
    "reference_price": 799.0,
    "single_weight_g": 4.8,
    "single_battery_h": 7.0,
    "total_battery_h": 32.0,
    "anc_supported": true,
    "anc_depth_db": 40.0,
    "dual_device": true,
    "low_latency": false,
    "bluetooth_version": 5.2,
    "waterproof": "IP55",
    "codec": null,
    "driver_size_mm": null,
    "source_url": "https://www.mi.com/xiaomibuds3",
    "manual_available": "是",
    "data_status": "部分缺失",
    "update_date": "2026-07-16",
    "remarks": "单次续航：最长7小时（降噪关）；最长5小时（降噪开）；总续航：最长32小时（降噪关）；最长23小时（降噪开）",
    "manual_url": "https://cdn.cnbj1.fds.api.mi-img.com/ics-resources/articles/640b03debb897d87d6d86ee8.html",
    "official_url": "https://www.mi.com/xiaomibuds3"
  },
  {
    "product_id": "EAR003",
    "product_name": "Redmi Buds 3 真无线蓝牙耳机",
    "model": "M2104E1",
    "brand": "REDMI",
    "category": "earphone",
    "product_level": "入门",
    "wearing_type": "半入耳式",
    "reference_price": 199.0,
    "single_weight_g": 4.5,
    "single_battery_h": 5.0,
    "total_battery_h": 20.0,
    "anc_supported": false,
    "anc_depth_db": null,
    "dual_device": false,
    "low_latency": true,
    "bluetooth_version": 5.2,
    "waterproof": "IP54",
    "codec": null,
    "driver_size_mm": null,
    "source_url": "https://www.mi.com/global/product/redmi-buds-3/",
    "manual_available": "是",
    "data_status": "部分缺失",
    "update_date": "2026-07-16",
    "remarks": null,
    "manual_url": "https://cdn.cnbj1.fds.api.mi-img.com/ics-resources/articles/63fd6a6428c901b30e2dffba.html",
    "official_url": "https://www.mi.com/global/product/redmi-buds-3/"
  },
  {
    "product_id": "EAR004",
    "product_name": "Redmi Buds 3 青春版",
    "model": "M2110E1",
    "brand": "REDMI",
    "category": "earphone",
    "product_level": "入门",
    "wearing_type": "入耳式",
    "reference_price": 99.0,
    "single_weight_g": 4.2,
    "single_battery_h": 5.0,
    "total_battery_h": 18.0,
    "anc_supported": false,
    "anc_depth_db": null,
    "dual_device": false,
    "low_latency": true,
    "bluetooth_version": 5.2,
    "waterproof": "IP54",
    "codec": null,
    "driver_size_mm": null,
    "source_url": "https://www.mi.com/redmibuds3lite",
    "manual_available": "是",
    "data_status": "部分缺失",
    "update_date": "2026-07-16",
    "remarks": null,
    "manual_url": "https://cdn.cnbj1.fds.api.mi-img.com/ics-resources/articles/63e459075adc341515bfc010.html",
    "official_url": "https://www.mi.com/redmibuds3lite"
  },
  {
    "product_id": "EAR005",
    "product_name": "Xiaomi Buds 4",
    "model": "M2224E1",
    "brand": "Xiaomi",
    "category": "earphone",
    "product_level": "高端",
    "wearing_type": "半入耳式",
    "reference_price": 999.0,
    "single_weight_g": 4.4,
    "single_battery_h": 6.0,
    "total_battery_h": 30.0,
    "anc_supported": true,
    "anc_depth_db": 48.0,
    "dual_device": true,
    "low_latency": false,
    "bluetooth_version": 5.3,
    "waterproof": "IP54",
    "codec": null,
    "driver_size_mm": null,
    "source_url": "https://www.mi.com/xiaomi-buds-4",
    "manual_available": "是",
    "data_status": "部分缺失",
    "update_date": "2026-07-16",
    "remarks": "单次续航：最长6小时（降噪关）；总续航：最长30小时（降噪关）；最长20小时（降噪开）",
    "manual_url": "https://cdn.cnbj1.fds.api.mi-img.com/ics-resources/articles/6396ea35a46ae5a17a443b07.html",
    "official_url": "https://www.mi.com/xiaomi-buds-4"
  },
  {
    "product_id": "EAR006",
    "product_name": "Redmi Buds 4 Pro",
    "model": "M2132E1",
    "brand": "REDMI",
    "category": "earphone",
    "product_level": "中端",
    "wearing_type": "入耳式",
    "reference_price": 399.0,
    "single_weight_g": 5.0,
    "single_battery_h": 9.0,
    "total_battery_h": 36.0,
    "anc_supported": true,
    "anc_depth_db": 43.0,
    "dual_device": true,
    "low_latency": true,
    "bluetooth_version": 5.3,
    "waterproof": "IP54",
    "codec": null,
    "driver_size_mm": null,
    "source_url": "https://www.mi.com/redmibuds4pro",
    "manual_available": "是",
    "data_status": "部分缺失",
    "update_date": "2026-07-16",
    "remarks": "单次续航：约9小时（降噪关）；总续航：约36小时（降噪关）",
    "manual_url": "https://cdn.cnbj1.fds.api.mi-img.com/ics-resources/articles/63e453c15adc341515bfb803.html",
    "official_url": "https://www.mi.com/redmibuds4pro"
  },
  {
    "product_id": "EAR007",
    "product_name": "Redmi Buds 4 青春版",
    "model": "M2231E1",
    "brand": "REDMI",
    "category": "earphone",
    "product_level": "入门",
    "wearing_type": "半入耳式",
    "reference_price": 129.0,
    "single_weight_g": 3.9,
    "single_battery_h": 5.0,
    "total_battery_h": 20.0,
    "anc_supported": false,
    "anc_depth_db": null,
    "dual_device": false,
    "low_latency": true,
    "bluetooth_version": 5.3,
    "waterproof": "IP54",
    "codec": null,
    "driver_size_mm": null,
    "source_url": "https://www.mi.com/redmi-buds-4-lite",
    "manual_available": "是",
    "data_status": "部分缺失",
    "update_date": "2026-07-16",
    "remarks": null,
    "manual_url": "https://cdn.cnbj1.fds.api.mi-img.com/ics-resources/articles/63abfa15aba6bc20c6a7e94f.html",
    "official_url": "https://www.mi.com/redmi-buds-4-lite"
  },
  {
    "product_id": "EAR008",
    "product_name": "Redmi Buds 4",
    "model": "M2137E1",
    "brand": "REDMI",
    "category": "earphone",
    "product_level": "中端",
    "wearing_type": "入耳式",
    "reference_price": 199.0,
    "single_weight_g": 4.5,
    "single_battery_h": 6.0,
    "total_battery_h": 30.0,
    "anc_supported": true,
    "anc_depth_db": 35.0,
    "dual_device": false,
    "low_latency": true,
    "bluetooth_version": 5.2,
    "waterproof": "IP54",
    "codec": null,
    "driver_size_mm": null,
    "source_url": "https://www.mi.com/redmibuds4",
    "manual_available": "是",
    "data_status": "部分缺失",
    "update_date": "2026-07-16",
    "remarks": "单次续航：约6小时（降噪关）；总续航：约30小时（降噪关）",
    "manual_url": "https://cdn.cnbj1.fds.api.mi-img.com/ics-resources/articles/640b011bbb897d87d6d85fe6.html",
    "official_url": "https://www.mi.com/redmibuds4"
  }
]
